gitbi/__init__.py
gitbi/git_bisector.py
gitbi-0.1.1.dist-info/METADATA
gitbi-0.1.1.dist-info/WHEEL
gitbi-0.1.1.dist-info/top_level.txt
gitbi-0.1.1.dist-info/RECORD
