Metadata-Version: 2.1
Name: gitbi
Version: 0.1.1
Summary: A tool for automating git bisect operations
Home-page: https://github.com/R-Peleg/python_git_bisector
Author: Reuven Peleg
Author-email: your.email@example.com
Classifier: Programming Language :: Python :: 3
Classifier: License :: OSI Approved :: MIT License
Classifier: Operating System :: OS Independent
Requires-Python: >=3.6
